{
    "images": [
        {
            "width": 2024,
            "height": 2024,
            "id": 1,
            "file_name": "PS_042_999.jpg"
        }
    ],
    "categories": [
        {
            "id": 1,
            "name": "pet"
        },
        {
            "id": 2,
            "name": "ps"
        },
        {
            "id": 3,
            "name": "pp"
        },
        {
            "id": 4,
            "name": "pe"
        }
    ],
    "annotations": [
        {
            "id": 1,
            "image_id": 1,
            "category_id": 2,
            "metainfo_id": 42,
            "segmentation": [
                [
                    397,
                    1276,
                    384,
                    1278,
                    375,
                    1290,
                    368,
                    1303,
                    362,
                    1316,
                    359,
                    1329,
                    354,
                    1342,
                    350,
                    1355,
                    345,
                    1368,
                    341,
                    1381,
                    339,
                    1394,
                    334,
                    1407,
                    331,
                    1420,
                    330,
                    1433,
                    328,
                    1446,
                    323,
                    1459,
                    321,
                    1472,
                    321,
                    1485,
                    321,
                    1498,
                    320,
                    1511,
                    319,
                    1524,
                    314,
                    1537,
                    312,
                    1550,
                    312,
                    1563,
                    315,
                    1576,
                    325,
                    1588,
                    338,
                    1591,
                    350,
                    1600,
                    363,
                    1604,
                    373,
                    1616,
                    384,
                    1626,
                    397,
                    1633,
                    409,
                    1643,
                    421,
                    1654,
                    433,
                    1661,
                    445,
                    1670,
                    456,
                    1664,
                    464,
                    1651,
                    469,
                    1638,
                    474,
                    1625,
                    484,
                    1618,
                    497,
                    1623,
                    510,
                    1630,
                    523,
                    1630,
                    536,
                    1625,
                    542,
                    1612,
                    549,
                    1599,
                    550,
                    1586,
                    554,
                    1573,
                    559,
                    1560,
                    561,
                    1547,
                    566,
                    1534,
                    569,
                    1521,
                    570,
                    1508,
                    571,
                    1495,
                    574,
                    1482,
                    577,
                    1469,
                    578,
                    1456,
                    578,
                    1443,
                    576,
                    1430,
                    572,
                    1417,
                    570,
                    1404,
                    569,
                    1391,
                    568,
                    1378,
                    568,
                    1365,
                    569,
                    1352,
                    569,
                    1339,
                    568,
                    1326,
                    558,
                    1317,
                    545,
                    1314,
                    532,
                    1317,
                    519,
                    1317,
                    506,
                    1316,
                    493,
                    1307,
                    480,
                    1305,
                    467,
                    1303,
                    455,
                    1294,
                    442,
                    1291,
                    429,
                    1287,
                    418,
                    1278,
                    405,
                    1276
                ]
            ],
            "bbox": [
                312,
                1276,
                266,
                394
            ],
            "ignore": 0,
            "iscrowd": 0,
            "area": 77250.5
        },
        {
            "id": 2,
            "image_id": 1,
            "category_id": 2,
            "metainfo_id": 42,
            "segmentation": [
                [
                    558,
                    977,
                    553,
                    980,
                    548,
                    982,
                    543,
                    985,
                    538,
                    988,
                    533,
                    991,
                    528,
                    995,
                    523,
                    998,
                    518,
                    1000,
                    513,
                    1001,
                    508,
                    1001,
                    503,
                    1002,
                    498,
                    1005,
                    493,
                    1007,
                    488,
                    1010,
                    483,
                    1012,
                    478,
                    1012,
                    473,
                    1012,
                    468,
                    1011,
                    463,
                    1011,
                    458,
                    1012,
                    453,
                    1014,
                    448,
                    1019,
                    443,
                    1023,
                    438,
                    1027,
                    434,
                    1032,
                    431,
                    1037,
                    430,
                    1042,
                    430,
                    1047,
                    430,
                    1052,
                    431,
                    1057,
                    431,
                    1062,
                    431,
                    1067,
                    431,
                    1072,
                    433,
                    1077,
                    434,
                    1082,
                    435,
                    1087,
                    440,
                    1092,
                    443,
                    1097,
                    448,
                    1100,
                    453,
                    1104,
                    458,
                    1107,
                    463,
                    1109,
                    468,
                    1109,
                    473,
                    1111,
                    478,
                    1112,
                    483,
                    1110,
                    488,
                    1109,
                    493,
                    1108,
                    498,
                    1107,
                    503,
                    1108,
                    508,
                    1110,
                    513,
                    1111,
                    518,
                    1110,
                    523,
                    1105,
                    527,
                    1100,
                    531,
                    1095,
                    534,
                    1090,
                    537,
                    1085,
                    538,
                    1080,
                    542,
                    1075,
                    544,
                    1070,
                    548,
                    1065,
                    550,
                    1060,
                    552,
                    1055,
                    554,
                    1050,
                    555,
                    1045,
                    559,
                    1040,
                    564,
                    1036,
                    569,
                    1032,
                    573,
                    1027,
                    578,
                    1022,
                    583,
                    1017,
                    586,
                    1012,
                    588,
                    1007,
                    588,
                    1002,
                    587,
                    997,
                    583,
                    992,
                    580,
                    988,
                    576,
                    983,
                    571,
                    979,
                    566,
                    977,
                    561,
                    977
                ]
            ],
            "bbox": [
                430,
                977,
                158,
                135
            ],
            "ignore": 0,
            "iscrowd": 0,
            "area": 13072.5
        },
        {
            "id": 3,
            "image_id": 1,
            "category_id": 2,
            "metainfo_id": 42,
            "segmentation": [
                [
                    586,
                    433,
                    581,
                    435,
                    576,
                    439,
                    572,
                    444,
                    569,
                    449,
                    566,
                    454,
                    562,
                    458,
                    558,
                    463,
                    554,
                    467,
                    551,
                    472,
                    547,
                    476,
                    542,
                    481,
                    538,
                    486,
                    535,
                    491,
                    533,
                    496,
                    531,
                    501,
                    530,
                    506,
                    531,
                    511,
                    531,
                    516,
                    534,
                    521,
                    538,
                    526,
                    543,
                    527,
                    548,
                    529,
                    553,
                    531,
                    558,
                    531,
                    563,
                    531,
                    568,
                    533,
                    572,
                    536,
                    573,
                    541,
                    575,
                    546,
                    579,
                    550,
                    584,
                    551,
                    589,
                    553,
                    594,
                    556,
                    599,
                    560,
                    602,
                    565,
                    605,
                    570,
                    610,
                    573,
                    615,
                    575,
                    620,
                    578,
                    625,
                    580,
                    630,
                    584,
                    635,
                    588,
                    640,
                    591,
                    645,
                    591,
                    650,
                    588,
                    654,
                    583,
                    659,
                    579,
                    663,
                    574,
                    667,
                    569,
                    671,
                    565,
                    676,
                    562,
                    681,
                    559,
                    683,
                    554,
                    684,
                    549,
                    682,
                    544,
                    679,
                    539,
                    676,
                    534,
                    673,
                    529,
                    670,
                    524,
                    669,
                    519,
                    668,
                    514,
                    667,
                    509,
                    666,
                    504,
                    666,
                    499,
                    666,
                    494,
                    664,
                    489,
                    660,
                    485,
                    655,
                    483,
                    650,
                    481,
                    645,
                    480,
                    640,
                    476,
                    635,
                    473,
                    631,
                    468,
                    628,
                    463,
                    625,
                    458,
                    624,
                    453,
                    623,
                    448,
                    619,
                    445,
                    614,
                    443,
                    609,
                    440,
                    604,
                    439,
                    599,
                    437,
                    594,
                    434,
                    589,
                    433
                ]
            ],
            "bbox": [
                530,
                433,
                154,
                158
            ],
            "ignore": 0,
            "iscrowd": 0,
            "area": 13838.5
        }
    ],
    "info": {
        "year": 2021,
        "version": "1.0",
        "contributor": "datamaker"
    },
    "metainfo": [
        {
            "id": 1,
            "name": "pet_식품용기류_투명_병류_대_비압축_라벨유",
            "category_id": 1,
            "container": true,
            "transparent": true,
            "shape": 0,
            "size": 0,
            "compress": 0,
            "label": true
        },
        {
            "id": 2,
            "name": "pet_식품용기류_투명_병류_대_비압축_라벨무",
            "category_id": 1,
            "container": true,
            "transparent": true,
            "shape": 0,
            "size": 0,
            "compress": 0,
            "label": false
        },
        {
            "id": 3,
            "name": "pet_식품용기류_투명_병류_대_수평압축_라벨유",
            "category_id": 1,
            "container": true,
            "transparent": true,
            "shape": 0,
            "size": 0,
            "compress": 1,
            "label": true
        },
        {
            "id": 4,
            "name": "pet_식품용기류_투명_병류_대_수평압축_라벨무",
            "category_id": 1,
            "container": true,
            "transparent": true,
            "shape": 0,
            "size": 0,
            "compress": 1,
            "label": false
        },
        {
            "id": 5,
            "name": "pet_식품용기류_투명_병류_대_수직압축_라벨유",
            "category_id": 1,
            "container": true,
            "transparent": true,
            "shape": 0,
            "size": 0,
            "compress": 2,
            "label": true
        },
        {
            "id": 6,
            "name": "pet_식품용기류_투명_병류_대_수직압축_라벨무",
            "category_id": 1,
            "container": true,
            "transparent": true,
            "shape": 0,
            "size": 0,
            "compress": 2,
            "label": false
        },
        {
            "id": 7,
            "name": "pet_식품용기류_투명_병류_소_비압축_라벨유",
            "category_id": 1,
            "container": true,
            "transparent": true,
            "shape": 0,
            "size": 1,
            "compress": 0,
            "label": true
        },
        {
            "id": 8,
            "name": "pet_식품용기류_투명_병류_소_비압축_라벨무",
            "category_id": 1,
            "container": true,
            "transparent": true,
            "shape": 0,
            "size": 1,
            "compress": 0,
            "label": false
        },
        {
            "id": 9,
            "name": "pet_식품용기류_투명_병류_소_수평압축_라벨유",
            "category_id": 1,
            "container": true,
            "transparent": true,
            "shape": 0,
            "size": 1,
            "compress": 1,
            "label": true
        },
        {
            "id": 10,
            "name": "pet_식품용기류_투명_병류_소_수평압축_라벨무",
            "category_id": 1,
            "container": true,
            "transparent": true,
            "shape": 0,
            "size": 1,
            "compress": 1,
            "label": false
        },
        {
            "id": 11,
            "name": "pet_식품용기류_투명_병류_소_수직압축_라벨유",
            "category_id": 1,
            "container": true,
            "transparent": true,
            "shape": 0,
            "size": 1,
            "compress": 2,
            "label": true
        },
        {
            "id": 12,
            "name": "pet_식품용기류_투명_병류_소_수직압축_라벨무",
            "category_id": 1,
            "container": true,
            "transparent": true,
            "shape": 0,
            "size": 1,
            "compress": 2,
            "label": false
        },
        {
            "id": 13,
            "name": "pet_식품용기류_불투명_병류_대_비압축_라벨유",
            "category_id": 1,
            "container": true,
            "transparent": false,
            "shape": 0,
            "size": 0,
            "compress": 0,
            "label": true
        },
        {
            "id": 14,
            "name": "pet_식품용기류_불투명_병류_대_비압축_라벨무",
            "category_id": 1,
            "container": true,
            "transparent": false,
            "shape": 0,
            "size": 0,
            "compress": 0,
            "label": false
        },
        {
            "id": 15,
            "name": "pet_식품용기류_불투명_병류_대_수평압축_라벨유",
            "category_id": 1,
            "container": true,
            "transparent": false,
            "shape": 0,
            "size": 0,
            "compress": 1,
            "label": true
        },
        {
            "id": 16,
            "name": "pet_식품용기류_불투명_병류_대_수평압축_라벨무",
            "category_id": 1,
            "container": true,
            "transparent": false,
            "shape": 0,
            "size": 0,
            "compress": 1,
            "label": false
        },
        {
            "id": 17,
            "name": "pet_식품용기류_불투명_병류_대_수직압축_라벨유",
            "category_id": 1,
            "container": true,
            "transparent": false,
            "shape": 0,
            "size": 0,
            "compress": 2,
            "label": true
        },
        {
            "id": 18,
            "name": "pet_식품용기류_불투명_병류_대_수직압축_라벨무",
            "category_id": 1,
            "container": true,
            "transparent": false,
            "shape": 0,
            "size": 0,
            "compress": 2,
            "label": false
        },
        {
            "id": 19,
            "name": "pet_식품용기류_불투명_병류_소_비압축_라벨유",
            "category_id": 1,
            "container": true,
            "transparent": false,
            "shape": 0,
            "size": 1,
            "compress": 0,
            "label": true
        },
        {
            "id": 20,
            "name": "pet_식품용기류_불투명_병류_소_비압축_라벨무",
            "category_id": 1,
            "container": true,
            "transparent": false,
            "shape": 0,
            "size": 1,
            "compress": 0,
            "label": false
        },
        {
            "id": 21,
            "name": "pet_식품용기류_불투명_병류_소_수평압축_라벨유",
            "category_id": 1,
            "container": true,
            "transparent": false,
            "shape": 0,
            "size": 1,
            "compress": 1,
            "label": true
        },
        {
            "id": 22,
            "name": "pet_식품용기류_불투명_병류_소_수평압축_라벨무",
            "category_id": 1,
            "container": true,
            "transparent": false,
            "shape": 0,
            "size": 1,
            "compress": 1,
            "label": false
        },
        {
            "id": 23,
            "name": "pet_식품용기류_불투명_병류_소_수직압축_라벨유",
            "category_id": 1,
            "container": true,
            "transparent": false,
            "shape": 0,
            "size": 1,
            "compress": 2,
            "label": true
        },
        {
            "id": 24,
            "name": "pet_식품용기류_불투명_병류_소_수직압축_라벨무",
            "category_id": 1,
            "container": true,
            "transparent": false,
            "shape": 0,
            "size": 1,
            "compress": 2,
            "label": false
        },
        {
            "id": 25,
            "name": "pet_식품용기류_투명_기타_대_비압축_라벨무",
            "category_id": 1,
            "container": true,
            "transparent": true,
            "shape": 3,
            "size": 0,
            "compress": 0,
            "label": false
        },
        {
            "id": 26,
            "name": "pet_식품용기류_투명_기타_대_수평압축_라벨무",
            "category_id": 1,
            "container": true,
            "transparent": true,
            "shape": 3,
            "size": 0,
            "compress": 1,
            "label": false
        },
        {
            "id": 27,
            "name": "pet_식품용기류_투명_기타_대_수직압축_라벨무",
            "category_id": 1,
            "container": true,
            "transparent": true,
            "shape": 3,
            "size": 0,
            "compress": 2,
            "label": false
        },
        {
            "id": 28,
            "name": "pet_식품용기류_투명_기타_소_비압축_라벨무",
            "category_id": 1,
            "container": true,
            "transparent": true,
            "shape": 3,
            "size": 1,
            "compress": 0,
            "label": false
        },
        {
            "id": 29,
            "name": "pet_식품용기류_투명_기타_소_수평압축_라벨무",
            "category_id": 1,
            "container": true,
            "transparent": true,
            "shape": 3,
            "size": 1,
            "compress": 1,
            "label": false
        },
        {
            "id": 30,
            "name": "pet_식품용기류_투명_기타_소_수직압축_라벨무",
            "category_id": 1,
            "container": true,
            "transparent": true,
            "shape": 3,
            "size": 1,
            "compress": 2,
            "label": false
        },
        {
            "id": 31,
            "name": "ps_식품용기류_불투명_기타_대_비압축_라벨무",
            "category_id": 2,
            "container": true,
            "transparent": false,
            "shape": 3,
            "size": 0,
            "compress": 0,
            "label": false
        },
        {
            "id": 32,
            "name": "ps_식품용기류_불투명_기타_대_수평압축_라벨무",
            "category_id": 2,
            "container": true,
            "transparent": false,
            "shape": 3,
            "size": 0,
            "compress": 1,
            "label": false
        },
        {
            "id": 33,
            "name": "ps_식품용기류_불투명_기타_대_수직압축_라벨무",
            "category_id": 2,
            "container": true,
            "transparent": false,
            "shape": 3,
            "size": 0,
            "compress": 2,
            "label": false
        },
        {
            "id": 34,
            "name": "ps_식품용기류_불투명_기타_소_비압축_라벨무",
            "category_id": 2,
            "container": true,
            "transparent": false,
            "shape": 3,
            "size": 1,
            "compress": 0,
            "label": false
        },
        {
            "id": 35,
            "name": "ps_식품용기류_불투명_기타_소_수평압축_라벨무",
            "category_id": 2,
            "container": true,
            "transparent": false,
            "shape": 3,
            "size": 1,
            "compress": 1,
            "label": false
        },
        {
            "id": 36,
            "name": "ps_식품용기류_불투명_기타_소_수직압축_라벨무",
            "category_id": 2,
            "container": true,
            "transparent": false,
            "shape": 3,
            "size": 1,
            "compress": 2,
            "label": false
        },
        {
            "id": 37,
            "name": "ps_식품용기류_불투명_병류_소_비압축_라벨유",
            "category_id": 2,
            "container": true,
            "transparent": false,
            "shape": 0,
            "size": 1,
            "compress": 0,
            "label": true
        },
        {
            "id": 38,
            "name": "ps_식품용기류_불투명_병류_소_비압축_라벨무",
            "category_id": 2,
            "container": true,
            "transparent": false,
            "shape": 0,
            "size": 1,
            "compress": 0,
            "label": false
        },
        {
            "id": 39,
            "name": "ps_식품용기류_불투명_병류_소_수평압축_라벨유",
            "category_id": 2,
            "container": true,
            "transparent": false,
            "shape": 0,
            "size": 1,
            "compress": 1,
            "label": true
        },
        {
            "id": 40,
            "name": "ps_식품용기류_불투명_병류_소_수평압축_라벨무",
            "category_id": 2,
            "container": true,
            "transparent": false,
            "shape": 0,
            "size": 1,
            "compress": 1,
            "label": false
        },
        {
            "id": 41,
            "name": "ps_식품용기류_불투명_병류_소_수직압축_라벨유",
            "category_id": 2,
            "container": true,
            "transparent": false,
            "shape": 0,
            "size": 1,
            "compress": 2,
            "label": true
        },
        {
            "id": 42,
            "name": "ps_식품용기류_불투명_병류_소_수직압축_라벨무",
            "category_id": 2,
            "container": true,
            "transparent": false,
            "shape": 0,
            "size": 1,
            "compress": 2,
            "label": false
        },
        {
            "id": 44,
            "name": "pp_식품용기류_불투명_원형_대_비압축_라벨무",
            "category_id": 3,
            "container": true,
            "transparent": false,
            "shape": 1,
            "size": 0,
            "compress": 0,
            "label": false
        },
        {
            "id": 46,
            "name": "pp_식품용기류_불투명_원형_대_수평압축_라벨무",
            "category_id": 3,
            "container": true,
            "transparent": false,
            "shape": 1,
            "size": 0,
            "compress": 1,
            "label": false
        },
        {
            "id": 48,
            "name": "pp_식품용기류_불투명_원형_대_수직압축_라벨무",
            "category_id": 3,
            "container": true,
            "transparent": false,
            "shape": 1,
            "size": 0,
            "compress": 2,
            "label": false
        },
        {
            "id": 50,
            "name": "pp_식품용기류_불투명_원형_소_비압축_라벨무",
            "category_id": 3,
            "container": true,
            "transparent": false,
            "shape": 1,
            "size": 1,
            "compress": 0,
            "label": false
        },
        {
            "id": 52,
            "name": "pp_식품용기류_불투명_원형_소_수평압축_라벨무",
            "category_id": 3,
            "container": true,
            "transparent": false,
            "shape": 1,
            "size": 1,
            "compress": 1,
            "label": false
        },
        {
            "id": 54,
            "name": "pp_식품용기류_불투명_원형_소_수직압축_라벨무",
            "category_id": 3,
            "container": true,
            "transparent": false,
            "shape": 1,
            "size": 1,
            "compress": 2,
            "label": false
        },
        {
            "id": 55,
            "name": "pp_식품용기류_불투명_사각형_대_비압축_라벨유",
            "category_id": 3,
            "container": true,
            "transparent": false,
            "shape": 2,
            "size": 0,
            "compress": 0,
            "label": true
        },
        {
            "id": 56,
            "name": "pp_식품용기류_불투명_사각형_대_비압축_라벨무",
            "category_id": 3,
            "container": true,
            "transparent": false,
            "shape": 2,
            "size": 0,
            "compress": 0,
            "label": false
        },
        {
            "id": 57,
            "name": "pp_식품용기류_불투명_사각형_대_수평압축_라벨유",
            "category_id": 3,
            "container": true,
            "transparent": false,
            "shape": 2,
            "size": 0,
            "compress": 1,
            "label": true
        },
        {
            "id": 58,
            "name": "pp_식품용기류_불투명_사각형_대_수평압축_라벨무",
            "category_id": 3,
            "container": true,
            "transparent": false,
            "shape": 2,
            "size": 0,
            "compress": 1,
            "label": false
        },
        {
            "id": 59,
            "name": "pp_식품용기류_불투명_사각형_대_수직압축_라벨유",
            "category_id": 3,
            "container": true,
            "transparent": false,
            "shape": 2,
            "size": 0,
            "compress": 2,
            "label": true
        },
        {
            "id": 60,
            "name": "pp_식품용기류_불투명_사각형_대_수직압축_라벨무",
            "category_id": 3,
            "container": true,
            "transparent": false,
            "shape": 2,
            "size": 0,
            "compress": 2,
            "label": false
        },
        {
            "id": 61,
            "name": "pp_식품용기류_불투명_사각형_소_비압축_라벨유",
            "category_id": 3,
            "container": true,
            "transparent": false,
            "shape": 2,
            "size": 1,
            "compress": 0,
            "label": true
        },
        {
            "id": 62,
            "name": "pp_식품용기류_불투명_사각형_소_비압축_라벨무",
            "category_id": 3,
            "container": true,
            "transparent": false,
            "shape": 2,
            "size": 1,
            "compress": 0,
            "label": false
        },
        {
            "id": 63,
            "name": "pp_식품용기류_불투명_사각형_소_수평압축_라벨유",
            "category_id": 3,
            "container": true,
            "transparent": false,
            "shape": 2,
            "size": 1,
            "compress": 1,
            "label": true
        },
        {
            "id": 64,
            "name": "pp_식품용기류_불투명_사각형_소_수평압축_라벨무",
            "category_id": 3,
            "container": true,
            "transparent": false,
            "shape": 2,
            "size": 1,
            "compress": 1,
            "label": false
        },
        {
            "id": 65,
            "name": "pp_식품용기류_불투명_사각형_소_수직압축_라벨유",
            "category_id": 3,
            "container": true,
            "transparent": false,
            "shape": 2,
            "size": 1,
            "compress": 2,
            "label": true
        },
        {
            "id": 66,
            "name": "pp_식품용기류_불투명_사각형_소_수직압축_라벨무",
            "category_id": 3,
            "container": true,
            "transparent": false,
            "shape": 2,
            "size": 1,
            "compress": 2,
            "label": false
        },
        {
            "id": 67,
            "name": "pp_기타_불투명_기타_기타_비압축_라벨무",
            "category_id": 3,
            "container": false,
            "transparent": false,
            "shape": 3,
            "size": 2,
            "compress": 0,
            "label": false
        },
        {
            "id": 68,
            "name": "pe_식품용기류_불투명_원형_대_비압축_라벨유",
            "category_id": 4,
            "container": true,
            "transparent": false,
            "shape": 1,
            "size": 0,
            "compress": 0,
            "label": true
        },
        {
            "id": 69,
            "name": "pe_식품용기류_불투명_원형_대_비압축_라벨무",
            "category_id": 4,
            "container": true,
            "transparent": false,
            "shape": 1,
            "size": 0,
            "compress": 0,
            "label": false
        },
        {
            "id": 70,
            "name": "pe_식품용기류_불투명_원형_대_수평압축_라벨유",
            "category_id": 4,
            "container": true,
            "transparent": false,
            "shape": 1,
            "size": 0,
            "compress": 1,
            "label": true
        },
        {
            "id": 71,
            "name": "pe_식품용기류_불투명_원형_대_수평압축_라벨무",
            "category_id": 4,
            "container": true,
            "transparent": false,
            "shape": 1,
            "size": 0,
            "compress": 1,
            "label": false
        },
        {
            "id": 72,
            "name": "pe_식품용기류_불투명_원형_대_수직압축_라벨유",
            "category_id": 4,
            "container": true,
            "transparent": false,
            "shape": 1,
            "size": 0,
            "compress": 2,
            "label": true
        },
        {
            "id": 73,
            "name": "pe_식품용기류_불투명_원형_대_수직압축_라벨무",
            "category_id": 4,
            "container": true,
            "transparent": false,
            "shape": 1,
            "size": 0,
            "compress": 2,
            "label": false
        },
        {
            "id": 74,
            "name": "pe_식품용기류_불투명_원형_소_비압축_라벨유",
            "category_id": 4,
            "container": true,
            "transparent": false,
            "shape": 1,
            "size": 1,
            "compress": 0,
            "label": true
        },
        {
            "id": 75,
            "name": "pe_식품용기류_불투명_원형_소_비압축_라벨무",
            "category_id": 4,
            "container": true,
            "transparent": false,
            "shape": 1,
            "size": 1,
            "compress": 0,
            "label": false
        },
        {
            "id": 76,
            "name": "pe_식품용기류_불투명_원형_소_수평압축_라벨유",
            "category_id": 4,
            "container": true,
            "transparent": false,
            "shape": 1,
            "size": 1,
            "compress": 1,
            "label": true
        },
        {
            "id": 77,
            "name": "pe_식품용기류_불투명_원형_소_수평압축_라벨무",
            "category_id": 4,
            "container": true,
            "transparent": false,
            "shape": 1,
            "size": 1,
            "compress": 1,
            "label": false
        },
        {
            "id": 78,
            "name": "pe_식품용기류_불투명_원형_소_수직압축_라벨유",
            "category_id": 4,
            "container": true,
            "transparent": false,
            "shape": 1,
            "size": 1,
            "compress": 2,
            "label": true
        },
        {
            "id": 79,
            "name": "pe_식품용기류_불투명_원형_소_수직압축_라벨무",
            "category_id": 4,
            "container": true,
            "transparent": false,
            "shape": 1,
            "size": 1,
            "compress": 2,
            "label": false
        },
        {
            "id": 80,
            "name": "pe_식품용기류_불투명_사각형_대_비압축_라벨유",
            "category_id": 4,
            "container": true,
            "transparent": false,
            "shape": 2,
            "size": 0,
            "compress": 0,
            "label": true
        },
        {
            "id": 81,
            "name": "pe_식품용기류_불투명_사각형_대_비압축_라벨무",
            "category_id": 4,
            "container": true,
            "transparent": false,
            "shape": 2,
            "size": 0,
            "compress": 0,
            "label": false
        },
        {
            "id": 82,
            "name": "pe_식품용기류_불투명_사각형_대_수평압축_라벨유",
            "category_id": 4,
            "container": true,
            "transparent": false,
            "shape": 2,
            "size": 0,
            "compress": 1,
            "label": true
        },
        {
            "id": 83,
            "name": "pe_식품용기류_불투명_사각형_대_수평압축_라벨무",
            "category_id": 4,
            "container": true,
            "transparent": false,
            "shape": 2,
            "size": 0,
            "compress": 1,
            "label": false
        },
        {
            "id": 84,
            "name": "pe_식품용기류_불투명_사각형_대_수직압축_라벨유",
            "category_id": 4,
            "container": true,
            "transparent": false,
            "shape": 2,
            "size": 0,
            "compress": 2,
            "label": true
        },
        {
            "id": 85,
            "name": "pe_식품용기류_불투명_사각형_대_수직압축_라벨무",
            "category_id": 4,
            "container": true,
            "transparent": false,
            "shape": 2,
            "size": 0,
            "compress": 2,
            "label": false
        },
        {
            "id": 86,
            "name": "pe_식품용기류_불투명_사각형_소_비압축_라벨유",
            "category_id": 4,
            "container": true,
            "transparent": false,
            "shape": 2,
            "size": 1,
            "compress": 0,
            "label": true
        },
        {
            "id": 87,
            "name": "pe_식품용기류_불투명_사각형_소_비압축_라벨무",
            "category_id": 4,
            "container": true,
            "transparent": false,
            "shape": 2,
            "size": 1,
            "compress": 0,
            "label": false
        },
        {
            "id": 88,
            "name": "pe_식품용기류_불투명_사각형_소_수평압축_라벨유",
            "category_id": 4,
            "container": true,
            "transparent": false,
            "shape": 2,
            "size": 1,
            "compress": 1,
            "label": true
        },
        {
            "id": 89,
            "name": "pe_식품용기류_불투명_사각형_소_수평압축_라벨무",
            "category_id": 4,
            "container": true,
            "transparent": false,
            "shape": 2,
            "size": 1,
            "compress": 1,
            "label": false
        },
        {
            "id": 90,
            "name": "pe_식품용기류_불투명_사각형_소_수직압축_라벨유",
            "category_id": 4,
            "container": true,
            "transparent": false,
            "shape": 2,
            "size": 1,
            "compress": 2,
            "label": true
        },
        {
            "id": 91,
            "name": "pe_식품용기류_불투명_사각형_소_수직압축_라벨무",
            "category_id": 4,
            "container": true,
            "transparent": false,
            "shape": 2,
            "size": 1,
            "compress": 2,
            "label": false
        },
        {
            "id": 92,
            "name": "pe_기타_불투명_기타_대_비압축_라벨유",
            "category_id": 4,
            "container": false,
            "transparent": false,
            "shape": 3,
            "size": 0,
            "compress": 0,
            "label": true
        },
        {
            "id": 93,
            "name": "pe_기타_불투명_기타_대_비압축_라벨무",
            "category_id": 4,
            "container": false,
            "transparent": false,
            "shape": 3,
            "size": 0,
            "compress": 0,
            "label": false
        },
        {
            "id": 94,
            "name": "pe_기타_불투명_기타_대_수평압축_라벨유",
            "category_id": 4,
            "container": false,
            "transparent": false,
            "shape": 3,
            "size": 0,
            "compress": 1,
            "label": true
        },
        {
            "id": 95,
            "name": "pe_기타_불투명_기타_대_수평압축_라벨무",
            "category_id": 4,
            "container": false,
            "transparent": false,
            "shape": 3,
            "size": 0,
            "compress": 1,
            "label": false
        },
        {
            "id": 96,
            "name": "pe_기타_불투명_기타_대_수직압축_라벨유",
            "category_id": 4,
            "container": false,
            "transparent": false,
            "shape": 3,
            "size": 0,
            "compress": 2,
            "label": true
        },
        {
            "id": 97,
            "name": "pe_기타_불투명_기타_대_수직압축_라벨무",
            "category_id": 4,
            "container": false,
            "transparent": false,
            "shape": 3,
            "size": 0,
            "compress": 2,
            "label": false
        },
        {
            "id": 98,
            "name": "pe_기타_불투명_기타_소_비압축_라벨유",
            "category_id": 4,
            "container": false,
            "transparent": false,
            "shape": 3,
            "size": 1,
            "compress": 0,
            "label": true
        },
        {
            "id": 99,
            "name": "pe_기타_불투명_기타_소_비압축_라벨무",
            "category_id": 4,
            "container": false,
            "transparent": false,
            "shape": 3,
            "size": 1,
            "compress": 0,
            "label": false
        },
        {
            "id": 100,
            "name": "pe_기타_불투명_기타_소_수평압축_라벨유",
            "category_id": 4,
            "container": false,
            "transparent": false,
            "shape": 3,
            "size": 1,
            "compress": 1,
            "label": true
        },
        {
            "id": 101,
            "name": "pe_기타_불투명_기타_소_수평압축_라벨무",
            "category_id": 4,
            "container": false,
            "transparent": false,
            "shape": 3,
            "size": 1,
            "compress": 1,
            "label": false
        },
        {
            "id": 102,
            "name": "pe_기타_불투명_기타_소_수직압축_라벨유",
            "category_id": 4,
            "container": false,
            "transparent": false,
            "shape": 3,
            "size": 1,
            "compress": 2,
            "label": true
        },
        {
            "id": 103,
            "name": "pe_기타_불투명_기타_소_수직압축_라벨무",
            "category_id": 4,
            "container": false,
            "transparent": false,
            "shape": 3,
            "size": 1,
            "compress": 2,
            "label": false
        }
    ]
}